<?xml version="1.0" encoding="UTF-8"?>
<knimeNode icon="./parquetreader-icon.png" type="Source" 
xmlns="http://knime.org/node/v3.1" 
xmlns:xsi="http://www.w3.org/2001/XMLSchema-instance" 
xsi:schemaLocation="http://knime.org/node/v3.1 http://knime.org/node/v3.1.xsd">

    <name>Parquet Reader</name>
    
    <shortDescription>
        Reader for Parquet files.
    </shortDescription>
    
    <fullDescription>
        <intro>Reader for Parquet files. It reads either single files or all files in a given directory.</intro>
         <tab name="Options">
     	   <option name="Input">The file or directory to read.</option>
        </tab>
        <tab name="Type Mapping">
         <description>
            Change the Parquet to KNIME type mapping configuration
            for subsequent nodes by selecting a KNIME type to the given
            Parquet Type.
            The dialog allows you to add new or change existing type mapping rules.
         </description>
         <option name="Mapping by Name">
            Columns that match the given name (or regular expression) and Parquet type will be mapped
            to the specified KNIME type.
         </option>
         <option name="Mapping by Type">
            Columns that match the given Parquet type will be mapped to the specified KNIME type.
         </option>
        </tab>
    </fullDescription>

    <ports>
        <inPort index="0" name="Remote connection port">Optional port for a remote connection.</inPort>
        <outPort index="0" name="Data table">Data table containing the data of the Parquet file.</outPort>
    </ports>    
</knimeNode>
